README.md
setup.py
src/envsubst_mustache/__init__.py
src/envsubst_mustache.egg-info/PKG-INFO
src/envsubst_mustache.egg-info/SOURCES.txt
src/envsubst_mustache.egg-info/dependency_links.txt
src/envsubst_mustache.egg-info/entry_points.txt
src/envsubst_mustache.egg-info/requires.txt
src/envsubst_mustache.egg-info/top_level.txt